{"id":"a1i3zaou9gkyufcx","createdAt":1708125320000,"updatedAt":1736868370936,"fileModified":0,"width":1024,"height":1024,"type":"images","title":"Athanasio.jpg","order":0,"filePath":"/loreforge-project-4ziocynu5ynj5xnj/image-files/Athanasio.jpg","fileName":"Athanasio.jpg","thumbFilePath":"\\loreforge-project-4ziocynu5ynj5xnj\\image-files\\thumbs\\a1i3zaou9gkyufcx.jpg","text":"","textPreview":"","altTitle":"","link":"","size":113410,"storyIds":[],"orgIds":[],"flagsOfOrgIds":[],"flagsOfLocationIds":[],"locationIds":[],"characterIds":[],"tagIds":[],"noteIds":[],"thingIds":[],"speciesIds":[],"discIds":[],"cultureIds":[]}