{"id":"rs4mbpo34afssk68","createdAt":1736524485861,"updatedAt":1736868370281,"fileModified":0,"width":921,"height":921,"type":"images","title":"Mizran Pasha.jpg","order":0,"filePath":"/loreforge-project-4ziocynu5ynj5xnj/image-files/Mizran Pasha.jpg","fileName":"Mizran Pasha.jpg","thumbFilePath":"\\loreforge-project-4ziocynu5ynj5xnj\\image-files\\thumbs\\rs4mbpo34afssk68.jpg","text":"","textPreview":"","altTitle":"","link":"","size":248021,"storyIds":[],"orgIds":[],"flagsOfOrgIds":[],"flagsOfLocationIds":[],"locationIds":[],"characterIds":["9a4ouwzh42ptd3y0"],"tagIds":[],"noteIds":[],"thingIds":[],"speciesIds":[],"discIds":[],"cultureIds":[]}